README.md
setup.cfg
setup.py
elih/__init__.py
elih/explanation.py
elih/features.py
elih/formatters.py
elih/helpers.py
elih/scoring.py
elih.egg-info/PKG-INFO
elih.egg-info/SOURCES.txt
elih.egg-info/dependency_links.txt
elih.egg-info/not-zip-safe
elih.egg-info/requires.txt
elih.egg-info/top_level.txt