Metadata-Version: 1.1
Name: elih
Version: 0.2.2
Summary: A library to translate Machine Learning classifiers predictions in a human understandable and simplified form.
Home-page: https://github.com/fvinas/elih
Author: Fabien Vinas
Author-email: fabien.vinas@gmail.com
License: UNKNOWN
Download-URL: https://github.com/fvinas/elih/archive/0.2.2.tar.gz
Platform: UNKNOWN
